odoo/addons/sale_invoice_blocking/README.rst
odoo/addons/sale_invoice_blocking/__init__.py
odoo/addons/sale_invoice_blocking/__manifest__.py
odoo/addons/sale_invoice_blocking/i18n/ca.po
odoo/addons/sale_invoice_blocking/i18n/es.po
odoo/addons/sale_invoice_blocking/i18n/es_PA.po
odoo/addons/sale_invoice_blocking/i18n/fr.po
odoo/addons/sale_invoice_blocking/i18n/sale_invoice_blocking.pot
odoo/addons/sale_invoice_blocking/models/__init__.py
odoo/addons/sale_invoice_blocking/models/invoice_blocking_reason.py
odoo/addons/sale_invoice_blocking/models/sale_order.py
odoo/addons/sale_invoice_blocking/readme/CONFIGURE.rst
odoo/addons/sale_invoice_blocking/readme/CONTRIBUTORS.rst
odoo/addons/sale_invoice_blocking/readme/DESCRIPTION.rst
odoo/addons/sale_invoice_blocking/readme/USAGE.rst
odoo/addons/sale_invoice_blocking/security/ir.model.access.csv
odoo/addons/sale_invoice_blocking/static/description/icon.png
odoo/addons/sale_invoice_blocking/static/description/index.html
odoo/addons/sale_invoice_blocking/views/menus.xml
odoo/addons/sale_invoice_blocking/views/sale_invoice_blocking_reason_view.xml
odoo/addons/sale_invoice_blocking/views/sale_order.xml
odoo14_addon_sale_invoice_blocking-14.0.1.0.1.dist-info/METADATA
odoo14_addon_sale_invoice_blocking-14.0.1.0.1.dist-info/WHEEL
odoo14_addon_sale_invoice_blocking-14.0.1.0.1.dist-info/top_level.txt
odoo14_addon_sale_invoice_blocking-14.0.1.0.1.dist-info/RECORD
